{
    "configurations": [
        {
            "name": "Linux",
            "includePath": [
                "${workspaceFolder}/**",
                "/usr/lib/gcc/x86_64-linux-gnu/13/include/**",
                "/usr/local/include/**",
                "/usr/include/x86_64-linux-gnu/**",
                "/usr/include/**",
                "/usr/include/mysql**"
            ],
            "defines": [],
            "compilerPath": "/usr/bin/gcc-9",
            "cStandard": "c23",
            "cppStandard": "c++14",
            "intelliSenseMode": "linux-gcc-arm"
        }
    ],
    "version": 4
}